vertibird.py
vertibird-0.1.7.dist-info/LICENSE
vertibird-0.1.7.dist-info/METADATA
vertibird-0.1.7.dist-info/WHEEL
vertibird-0.1.7.dist-info/top_level.txt
vertibird-0.1.7.dist-info/RECORD
