Metadata-Version: 2.1
Name: vertibird
Version: 0.1.7
Summary: A really, really simple Python virtualization module which interfaces directly with QEMU.
Home-page: https://github.com/naphthasl/vertibird
Author: Naphtha Nepanthez
Author-email: naphtha@lotte.link
License: MIT
Platform: any
Classifier: Intended Audience :: Developers
Classifier: License :: OSI Approved :: MIT License
Classifier: Programming Language :: Python :: 3
Classifier: Programming Language :: Python :: 3.4
Classifier: Programming Language :: Python :: 3.5
Classifier: Programming Language :: Python :: 3.6
Classifier: Programming Language :: Python :: 3.7
Classifier: Programming Language :: Python :: 3.8
Requires-Python: >=3.6
Requires-Dist: sqlalchemy
Requires-Dist: pillow-simd
Requires-Dist: vncdotool
Requires-Dist: numpy
Requires-Dist: opencv-python
Requires-Dist: psutil
Requires-Dist: filelock
Requires-Dist: pyzmq
Requires-Dist: python-dateutil
Requires-Dist: yunyundb
